{

    "PACO":{
        "frases":
        [
            { "texto": "España va cuesta abajo, y no por falta de ideas,", "author": "Paco" },
            { "texto": "sino porque los políticos están más ocupados robando que gobernando.", "author": "Paco" },
            { "texto": "Cada semana un escándalo nuevo: sobres, contratos amañados… ¡y ninguno dimite!", "author": "Paco" },
            { "texto": "Sobretodo esa dichosa Yusoa... no se puede ser más descarada.", "author": "Paco" },
            { "texto": "La gente está harta, pero cansada, como si ya ni nos quedaran fuerzas para enfadarnos.", "author": "Paco" },
            { "texto": "Y mientras ellos se reparten el pastel, a nosotros nos suben todo menos el sueldo.", "author": "Paco" },
            { "texto": "Esto, chaval, no es país, es un chiste malo.", "author": "Paco" }
            
        ],
        "hablado": "false",
        "scale": 0.5,
        "recompensa": "humildad"
    },
    "ÁNGEL":{
        "frases":
        [
            { "texto": "Ey compañere, ¿Te trata bien la vida?", "author": "Ángel" },
            { "texto": "Porque a mi no me tratan muy bien. -suspira- ", "author": "Ángel" },
            { "texto": "Mi grupo Los Granos de Yusoa, hemos tenido que separarnos.", "author": "Ángel" },
            { "texto": "No contamos con pasta suficiente y la mitad del grupo está en rehabilitación.", "author": "Ángel" },
            { "texto": "Con el futuro prometodor que teníamos y van y lo tiran por la borda.", "author": "Ángel" },
            { "texto": "Aunque tampoco les culpo.", "author": "Ángel" },
            { "texto": "En esta ciudad o tomas algo o te vuelves completamente loco.", "author": "Ángel" }
        ],
        "hablado": "false",
        "scale": 0.5,
        "recompensa": "trabajo duro"
    },
    "HUMBERTO":{

        "frases":
        [
            { "texto": "Hola chavale, buenas mañas. Hoy hace un tiempo buenísimo para cabalgar un poco, ¿no crees?", "author": "Humberto" },
            { "texto": "Las apuestas esta semana están muy altas, ¿Te apuntas?", "author": "Humberto" },
            { "texto": "Me he comprado un vinito para disfrutar mientras veo las carreras,", "author": "Humberto" },
            { "texto": "Estoy seguro de que mis jinetes ganarán esta semana de nuevo.", "author": "Humberto" },
            { "texto": "¡Jajaja! me voy a hacer de oro", "author": "Humberto" },
            { "texto": "Mi caballo Sardinilla es el mejor de todos, no hay quien le gane.", "author": "Humberto" }
        ],
        "hablado": "false",
        "scale": 0.5,
        "recompensa": "afecto"
    },
    "JOSÉ":{

        "frases":
        [
            { "texto": "¿Qué tal maquina?, ¿te gustan los caballos?", "author": "Jose" },
            { "texto": "Humberto no sabe nada de ellos y se cree que el suyo va a ganar la carrera", "author": "Jose" },
            { "texto": "No se lo cree ni él ¡jajaja!, mi caballo Lentejilla va a ser el ganador ", "author": "Jose" },
            { "texto": "¡Vamos vamos apuesta por mi Lentejilla ya verás que te harás con un buen botín!", "author": "Jose" }
        ],
        "hablado": "false",
        "scale": 0.5,
        "recompensa": "humildad"
    },
    "MARÍA":{

        "frases":
        [
            { "texto": "No me lo puedo creer, me han vuelto a excluir de la reunión.", "author": "Maria" },
            { "texto": "Siempre igual, no me tienen en cuenta para nada.", "author": "Maria" },
            { "texto": "Siempre me toca hacer el trabajo sucio...", "author": "Maria" },
            { "texto": "Y ¿para qué? Para que me ignoren y me dejen de lado.", "author": "Maria" },
            { "texto": "La corrupción de la presidencia es evidente, no se puede ser más descarado,", "author": "Maria" },
            { "texto": "Pero a mí nadie me hace ni caso.", "author": "Maria" },
            { "texto": "¡Ni siquiera parece que sea presidenta de cámara! Es una vergüenza.", "author": "Maria" },
            { "texto": "Sin embargo, cuando Yusoa se lava las manos tras crear leyes injustas que solo benefician a los ricos,", "author": "Maria" },
            { "texto": "Nadie dice nada.", "author": "Maria" }
        ],
        "hablado": "false",
        "scale": 0.5,
        "recompensa": "trabajo duro"
        
    },
    "PEDRITO":{

        "frases":
        [
            { "texto": "¿Sabías que esta cámara se fundó en 1823 y que el arquitecto fue mi bisabuelo?", "author": "Pedrito" },
            { "texto": "A que no eh, jejeje", "author": "Pedrito" },
            { "texto": "Con el legado que me dejó mi familia y yo soy un simple secretario de la presidenta de la cámara", "author": "Pedrito" },
            { "texto": "Ella no aprecia lo suficiente su puesto y siempre se queja", "author": "Pedrito" },
            { "texto": "Si yo fuese presidente de la cámara haria las cosas mejor que ella desde luego", "author": "Pedrito" },
            { "texto": "Algún día lo conseguire", "author": "Pedrito" }
        ],
        "hablado": "false",
        "scale": 0.5,
        "recompensa": "afecto"
        
    },
    "CONSUELO":{

        "frases":
        [
            { "texto": "Mira yo no doy a basto, ugh...", "author": "Consuelo" },
            { "texto": "Cada día que pasa hay más gente que entra en nuestra clínica de desintoxicación.", "author": "Consuelo" },
            { "texto": "Lo peor de la situación es que muchos entran obligados,", "author": "Consuelo" },
            { "texto": "Por tanto no son proclives a soltar la botella.", "author": "Consuelo" },
            { "texto": "Por más que intentemos concienciar a la gente, no es suficiente.", "author": "Consuelo" },
            { "texto": "Las cifras de nuevos ingresos están aumentando frenéticamente.", "author": "Consuelo" },
            { "texto": "No comprenden que están echando a perder sus vidas,", "author": "Consuelo" },
            { "texto": "Y haciendo sufrir a sus seres queridos,", "author": "Consuelo" },
            { "texto": "El alcoholismo solo trae dolor.", "author": "Consuelo" }

        ],
        "hablado": "false",
        "scale": 0.5,
        "recompensa": "agnosticismo"
    },
    "MARÍA TERESA":{

        "frases":
        [
            { "texto": "Estoy agradecida de poder trabajar aquí,", "author": "Maria Teresa" },
            { "texto": "Siempre me agradó poder ayudar a las personas.", "author": "Maria Teresa" },
            { "texto": "Si tan solo el jefe dejara de lado sus prejuicios...", "author": "Maria Teresa" },
            { "texto": "No me malinterpretes, es una persona encantadora, pero...", "author": "Maria Teresa" },
            { "texto": "A veces no se da cuenta que debería amar a todos por igual y respetar.", "author": "Maria Teresa" },
            { "texto": "Eso es lo que nos enseñó Jesús, ¿no?", "author": "Maria Teresa" }
        ],
        "hablado": "false",
        "scale": 0.5,
        "recompensa": "humildad"
    },
    "ALI":{

        "frases":
        [
            { "texto": "¿Has oído hablar del cura de la iglesia de al lado?", "author": "Ali" },
            { "texto": "está casi al final del distrito, el cura se encuenta en ella,", "author": "Ali" },
            { "texto": "aunque siempre actúa raro y de manera sospechosa, nadie nunca le contradice.", "author": "Ali" },
            { "texto": "Además últimamente han desaparecido muchos niños en el barrio.", "author": "Ali" },
            { "texto": "Creo que ha podido ser él, ojalá alguien le pare los pies.", "author": "Ali" },
            { "texto": "Realmente es horrible lo que algunos adultos pueden llegar a hacer...", "author": "Ali" }
        ],
        "hablado": "false",
        "recompensa": "agnosticismo"
    },
    "MARÍA DEL CARMEN":{
        "frases":
        [
            { "texto": "Si tan solo ella fuera un chico...", "author": "Maria del Carmen" },
            { "texto": "¡Oh! perdón, no te había visto amigue.", "author": "Maria del Carmen" },
            { "texto": "Siento que me tengas que ver así, pero ahora mismo no estoy pasando por el mejor momento.", "author": "Maria del Carmen" },
            { "texto": "María Jose se me ha declarado y yo... la quiero mucho.", "author": "Maria del Carmen" },
            { "texto": "Pero, ¿yo soy hetero...?", "author": "Maria del Carmen" },
            { "texto": "Igualmente, si no lo fuera, mi familia nunca me aceptaría.", "author": "Maria del Carmen" },
            { "texto": "Y podría meterme en graves problemas.", "author": "Maria del Carmen" },
            { "texto": "María Jose, perdón por no ser valiente.", "author": "Maria del Carmen" }
        ],
        "hablado": "false",
        "scale": 0.5,
        "recompensa": "trabajo duro"
    },
    "MARÍA JOSÉ":{
        "frases":
        [
            { "texto": "Buenas compañere.", "author": "Maria Jose" },
            { "texto": "¿Tu también tienes dolor de corazón?", "author": "Maria Jose" },
            { "texto": "De verdad, esta ciudad me quita todo lo que quiero.", "author": "Maria Jose" },
            { "texto": "Primero, pierdo a mis padres por las drogas y el alcohol.", "author": "Maria Jose" },
            { "texto": "Y después, la única mujer a la que he querido me rechaza ¿porque es hetero?", "author": "Maria Jose" },
            { "texto": "Si claro, ni ella misma se lo cree.", "author": "Maria Jose" },
            { "texto": "Tiene miedo, como todos en esta ciudad.", "author": "Maria Jose" },
            { "texto": "Creo que ya es hora de que huya de aquí.", "author": "Maria Jose" },
            { "texto": "Si tan solo Maria del Carmen viniera conmigo...", "author": "Maria Jose" }
        ],
        "hablado": "false",
        "scale": 0.5,
        "recompensa": "afecto"
    },
    "JESÚS":{
        "frases":
        [
            { "texto": "Oh querido hermane, ¿qué te trae por este lugar?", "author": "Jesus" },
            { "texto": "El otro dia un ave blanca me reveló mi destino", "author": "Jesus" },
            { "texto": "Me dijo que me sacrificaría por todos mis vecinos", "author": "Jesus" },
            { "texto": "Y que después de 3 días lograría despertar del sueño eterno", "author": "Jesus" },
            { "texto": "Se me ha encomendado esta divina tarea a mi, un simple ex-carpintero que ahora deambula estas calles sin hogar ni trabajo ", "author": "Jesus" },
            { "texto": "Debo de seguir bebiendo de este vino bendito para volver a verla y preguntarla más acerca de mi enmienda.", "author": "Jesus" }
        ],
        "hablado": "false",
        "scale": 0.5,
        "recompensa": "humildad"
    },
    "GATO EN CAJA":{

        "frases":
        [
            { "texto": "Miauu, Marramau mau", "author": "Gato" },
            { "texto": "(Ey ey pequeñe,¿Has socializado con la gente no?)", "author": "Gato" },
            { "texto": "miiiaau marrau miau", "author": "Gato" },
            { "texto": "Tengo algo golosón que seguro que te interesa", "author": "Gato" }
        ],
        "hablado": "false",
        "scale": 0.4,
        "recompensa": "trabajo duro"
    },
    "ELLIE":{
        "frases":[
            { "video": "intro" },
            
            { "texto": "¿Holaa? Persona desconocida, ¿Respiras?, ¿Estás bien?", "author": "???" },
            { "texto": "Hola. Ay! Me duele el abdomen, creo que me han golpeado", "author": "Elle" },
            { "texto": "Por fin, llevo intentando despertarte un tiempo, pensaba que te habías ido al otro barrio.", "author": "???" },
            { "texto": "Pues por como están la cosas en nuestra sociedad casi que lo hubiese preferido.", "author": "Elle" },
            { "texto": "Por cierto, ¿Ya ha acabado la manifestación? Que veo que es casi de noche ya.", "author": "Elle" },
            { "texto": "¿Qué manifestación?", "author": "???" },
            { "texto": "La que estaba organizada hoy aquí, para recuperar los derechos que ese tirano del alcalde nos quería quitar.", "author": "Elle" },
            { "texto": "¿Alcalde? JAJAJAJA, casi que hubiese preferido eso, lo que tenemos ahora al mando es una repugnante dictadora.", "author": "???" },
            { "texto": "¿Cómo es que en pleno siglo 21 haya dictadores en Madrizz? ¿No te estás liando?", "author": "Elle" },
            { "texto": "Pero, ¿Qué estás diciendo? Estamos en el año 22V-4, ....., ¡Espera!, ¡¿Vienes del pasado?!", "author": "???" },
            { "texto": "Con que el futuro... ya decía yo que notaba los alrededores muy raros.", "author": "Elle" },
            { "texto": "Pues que bien, hasta en el futuro seguimos oprimidos.", "author": "Elle" },
            { "texto": "Por cierto, soy Elle y ahora que me acuerdo estábamos en plena manifestación cuando un policia me atizó con su porra", "author": "Elle" },
            { "texto": "Y de alguna manera he acabado aqui.", "author": "Elle" },
            { "texto": "Buenas, yo soy Ellie, y déjame decirte que aquí estamos incluso peor.", "author": "Ellie" },
            { "texto": "Te hago un pequeño resumen.", "author": "Ellie" },
            
            { "video": "resumen" },

            { "texto": "Ahora, los únicos que intentamos luchar contra el sistema, somos nosotros.", "author": "Ellie" },
            { "texto": "Dejarme ayudaros, no puedo quedarme solo mirando, sin hacer nada.", "author": "Elle" },
            { "texto": "¡Luchemos para que ni nosotros ni las futuras generaciones tengan que aguantar lo que nosotros estamos viviendo!", "author": "Elle" },
            { "texto": "Me gusta tu espíritu, Elle.", "author": "Ellie" },
            { "texto": "Gente con tu fortaleza y tu ímpetu es lo que nos hace falta.", "author": "Ellie" },
            { "texto": "¿Cómo puedo empezar con esto?", "author": "Elle" },
            { "texto": "Puedes comenzar hablando con los vecinos de los diferentes barrios,", "author": "Ellie" },
            { "texto": "Ellos te pueden dar objetos útiles para la batalla con el jefe del barrio cuando te enfrentes a él.", "author": "Ellie" },
            { "texto": "¿Hablar con gente? Yo soy más de actuar.", "author": "Elle" },
            { "texto": "Pero bueno, ¿Cómo puedo ir de un barrio a otro?", "author": "Elle" },
            { "texto": "Facilito, pilla la Tenfe,", "author": "Ellie" },
            { "texto": "Pero, mucha suerte con eso, casi nunca funciona correctamente. Yusoa nos ha quitado los derechos pero, eh, la tenfe nos la ha dejado", "author": "Ellie" },
            { "texto": "Entiendo, pero aunque me veas bastante motivade, hablar con mucha gente nueva me da ansiedad.", "author": "Elle" },
            { "texto": "Pues piensa muy bien con qué vecinos hablar, y si estás muy mal siempre puedes fumarte un piti en el banco.", "author": "Ellie" },
            { "texto": "Todo claro ahora, ¿no?", "author": "Ellie" },
            { "texto": "Recuperar trozos de constitución para juntarlos y llegar a la zona donde está YUSOA para recuperar nuestros derechos.", "author": "Ellie" },
            { "texto": "Al lio.", "author": "Elle" }

        ],
        "hablado": "false",
        "scale": 0.5
        
    },
    "ALADIN":{
        "frases":
        [
            { "texto": "مرحباً (hola)", "author": "Aladin" },
            { "texto": "Querido amige tu país es espléndido.", "author": "Aladin" },
            { "texto": "La cultura (para nada heredada),la comida,el paisaje.", "author": "Aladin" },
            { "texto": "Por cierto, ¿tienes contacto con el gobernador de este país?", "author": "Aladin" },
            { "texto": "Porque me encantaría proponer algunos tratados de negocios", "author": "Aladin" },
            { "texto": "que podría tener muchos beneficios para ambos países.", "author": "Aladin" }
        ],
        "hablado": "false",
        "scale": 0.5,
        "recompensa": "humildad"
    },
    "PELAYO":{
        "frases":
        [
            { "texto": "Eh Eh, ¿Has visto el saque de revés que he hecho?", "author": "Pelayo" },
            { "texto": "Impresionante, ¿a que sí?", "author": "Pelayo" },
            { "texto": "No es por fardar pero entrené en la academia de Rafir Nadl.", "author": "Pelayo" },
            { "texto": "Si es que somos igualitos.", "author": "Pelayo" },
            { "texto": "Misma técnica, mismos saques, se podría hasta decir que soy su sucesor.", "author": "Pelayo" },
            { "texto": "Si es que que bueno que soy.", "author": "Pelayo" }
        ],
        "hablado": "false",
        "scale": 0.5,
        "recompensa": "humildad"
    },
    "ADELINA":{
        "frases":
        [
            { "texto": "Juntamos los brazos y notamos como toda la tensión de nuestro cuerpo desaparece.", "author": "Adelina" },
            { "texto": "Inspiramos y expiramos.", "author": "Adelina" },
            { "texto": "¿Interesade en unas clases de yoga?", "author": "Adelina" },
            { "texto": "Te ayuda a recobrar el control sobre ti misme y es un momento ideal para practicar mindfulness.", "author": "Adelina" },
            { "texto": " Aprovecha, es una oportunidad única en la vida.", "author": "Adelina" }
        ],
        "hablado": "false",
        "scale": 0.5,
        "recompensa": "humildad"
    },
    "CAYETANA":{
        "frases":
        [
            { "texto": "Osea tie, ¿Has visto el nuevo bolso que ha salido de la nueva línea de Luan Lutoni?", "author": "Cayetana" },
            { "texto": "Buah tie, es super bonito con un encaje violeta, y hecho de un material super duradero poli... no se que.", "author": "Cayetana" },
            { "texto": "Si es que es una ganga 40000 euros.", "author": "Cayetana" },
            { "texto": "No se por qué papi no me lo quiere comprar", "author": "Cayetana" },
            { "texto": "Si solo he suspendido una asignatura.", "author": "Cayetana" },
            { "texto": "Bueno, y esa también... y aquella... y otra…", "author": "Cayetana" }
        ],
        "hablado": "false",
        "scale": 0.5,
        "recompensa": "humildad"
    },
    "GREGORIO":{
        "frases":
        [
            { "texto": "¡FIIIIRMEEEEES!", "author": "Gregorio" },
            { "texto": "Esta juventud ya no respeta a los veteranos de la guerra.", "author": "Gregorio" },
            { "texto": "Cuando yo tenía tu edad me aliste en el ejército y me desplegaron en Marruecos.", "author": "Gregorio" },
            { "texto": "Esta insignia la gané por mi estupenda labor, mira tiene grabada una espléndida ave.", "author": "Gregorio" },
            { "texto": "Esta ave fue de vital importancia en toda mi juventud y adultez.", "author": "Gregorio" },
            { "texto": "Que cariño le tengo...", "author": "Gregorio" }
        ],
        "hablado": "false",
        "scale": 0.5,
        "recompensa": "humildad"
    },
    "KAREN":{
        "frases":
        [
            { "texto": "¡INDIGNANTE!", "author": "Karen" },
            { "texto": "El otro día fui con mi familia a uno de los mejores restaurantes del país y nos trajeron los platos con bastante retraso.", "author": "Karen" },
            { "texto": "¡15 MINUTOS! ¡INDIGNANTE! ¡MIRES POR DONDE LO MIRES!", "author": "Karen" },
            { "texto": "Y como es normal, solicité la hoja de reclamaciones.", "author": "Karen" },
            { "texto": "Y tienen la poca vergüenza de decirnos que es el tiempo normal de espera.", "author": "Karen" },
            { "texto": "¡INDIGNANTE! Les voy a demandar.", "author": "Karen" }
        ],
        "hablado": "false",
        "scale": 0.5,
        "recompensa": "humildad"
    },
    "HILARIO":{
        "frases":
        [
            { "texto": "Heredé el oficio de mi padre, como hizo mi padre de su padre y así durante generaciones.", "author": "Hilario" },
            { "texto": "Los Hnos Ortiz llevan en el negocio de la panadería cientos de años y está tienda siempre ha tenido sus clientes fieles.", "author": "Hilario" },
            { "texto": "Ahora con la apertura de centros comerciales solo los clientes más longevos vienen a comprar.", "author": "Hilario" },
            { "texto": "Esta situación es desesperante pero yo sé que este negocio sobrevivirá.", "author": "Hilario" },
            { "texto": "Que las nuevas generaciones aprenderán a apreciar la calidad de nuestros productos.", "author": "Hilario" }
            
        ],
        "hablado": "false",
        "scale": 0.5,
        "recompensa": "humildad"
    },
    "JULIANA":{
        "frases":
        [
            { "texto": "¿Sabes hasta que cifra ha subido el abandono escolar?", "author": "Juliana" },
            { "texto": "Se ha cuadruplicado.", "author": "Juliana" },
            { "texto": "De verdad que estoy muy preocupada.", "author": "Juliana" },
            { "texto": "¿Cómo puede ser que un adolescente de 16 años, a lo sumo, quiera abandonar el instituto?", "author": "Juliana" },
            { "texto": "Si, hay que echarle horas a los estudios. Pero, ¿a qué chaval no le gusta estar un rato con sus compañeros en clase?", "author": "Juliana" },
            { "texto": "Es todo culpa del gobernador.", "author": "Juliana" },
            { "texto": "Que nos da muy pocas subvenciones para ayudar a estos chavales con pocos recursos a seguir estudiando.", "author": "Juliana" }
        ],
        "hablado": "false",
        "scale": 0.5,
        "recompensa": "humildad"
    },
    "MANOLO":{
        "frases":
        [
            { "texto": "¿Conoces la empresa de paquetería TCT?", "author": "Manolo" },
            { "texto": "Pues si estás pensando en echar currículum...", "author": "Manolo" },
            { "texto": "¡NI SE TE OCURRA! LOS GERENTES SON UNOS ***** *******. POR NO HABLAR DEL JEFE.", "author": "Manolo" },
            { "texto": "Perdón, pero sacan lo peor de mi. Es que es horrible de verdad.", "author": "Manolo" },
            { "texto": "Solo he trabajado un 1 año con ellos y ya no puedo más.", "author": "Manolo" },
            { "texto": "Los de recursos humanos están comprados por el jefe y si te quejas de trato indebido o injusto les da absolutamente igual.", "author": "Manolo" },
            { "texto": "A mí no me vuelven a ver la cara.", "author": "Manolo" }
        ],
        "hablado": "false",
        "scale": 0.5,
        "recompensa": "humildad"
    },
    "MIHAI":{
        "frases":
        [
            { "texto": "Eyyy colegaaa ¿qué taaaaal??", "author": "Mihai" },
            { "texto": "Yo estoy super chili.", "author": "Karen" },
            { "texto": "No veas cómo la gente pide pizzas. Eh, una tras otra, tras otra,", "author": "Karen" },
            { "texto": "Pero, eehh, tranqui colegui que si quieres un descuento podemos hacer un trato guapo guapo.", "author": "Karen" },
            { "texto": "Tu me das un gramito y yo te doy un descuentito, ¿oferton, eh?", "author": "Karen" }
        ],
        "hablado": "false",
        "scale": 0.5,
        "recompensa": "humildad"
    },
    "NICOLETA":{
        "frases":
        [
            { "texto": "¡6 DIAS A LA SEMANA!", "author": "Nicoleta" },
            { "texto": "¡TODO EL DIA con DOS míseros descansos de 1 h para comer y cenar!", "author": "Nicoleta" },
            { "texto": "Encima, me pagan una miseria para todo el trabajo que hago.", "author": "Nicoleta" },
            { "texto": "De verdad, que estoy que echo humo, pero necesito este curro.", "author": "Nicoleta" },
            { "texto": "¿Cómo si no voy a poder pagar mi apartamento y alimentar a mi gato Kuskus?", "author": "Nicoleta" }
        ],
        "hablado": "false",
        "scale": 0.5,
        "recompensa": "humildad"
    },
    "SUSANA":{
        "frases":
        [
            { "texto": "Susana dobla estás camisetas que las han dejado tiradas,", "author": "Susana" },
            { "texto": "Susana recoge todos estos pares de pantalones,", "author": "Susana" },
            { "texto": "Susana estos zapatos los han dejado descolocados, colócalos para que los clientes los vean bien,", "author": "Susana" },
            { "texto": "Susana esto, Susana lo otro...", "author": "Susana" },
            { "texto": "¡MADRE MIA! ¿¡CÓMO PUEDEN SER ESOS SERES HUMANOS LLAMADOS CLIENTES TAN DESORDENADOS¡?", "author": "Susana" },
            { "texto": "Aguanta solo dos semanas más y podrás comprarle a papá esas medicaciones que necesita para el tratamiento.", "author": "Susana" }
        ],
        "hablado": "false",
        "scale": 0.5,
        "recompensa": "humildad"
    },
    "COPAS":
    {
        "frases":[
            { "texto": "Hola pequeñe, ¿vienes al sermón de hoy?", "author": "Copas" },
            { "texto": "Toma asiento al fondo y mantente calladite.", "author": "Copas" },
            { "texto": "No queremos que te pase nada, ¿no crees?", "author": "Copas" },
            { "texto": "No vengo a escucharte hablar, momia andante", "author": "Elle" },
            { "texto": "He cookeado y estoy aquí para poner fin a tu reinado de terror en este barrio.", "author": "Elle" },
            { "texto": "Dame el trozo de constitución que tienes y huye de aquí, primera y última advertencia.", "author": "Elle" },
            { "texto": "JAJAJAJAJA, vaya humos tienes para tener un cuerpo tan pequeño.", "author": "Copas" },
            { "texto": "¿Realmente piensas que un niñate como tú puede derrotarme?", "author": "Copas" },
            { "texto": "Adelante, intentalo. Tengo muchas ganas de comerte vivo.", "author": "Copas" }
        ],
        "victory":[
            { "texto": "AAAAAGGGGGHHHHHHHH", "author": "Copas" },
            { "texto": "¿Eso es todo tu poder? Hasta la monja de aquí al lado podría haberte ganado", "author": "Elle" },
            { "texto": "Te me relajas con la humillación.", "author": "Copas" },
            { "texto": "Toma la maldita constitución y lárgate de aquí.", "author": "Copas" },
            { "texto": "Eso no es suficiente, debes marcharte de aquí inmediatamente.", "author": "Elle" },
            { "texto": "Que sí, que sí. Pero que primero tengo que coger un tren y ya sabes como funciona Tenfe.", "author": "Copas" }
        ],
        "lose":[
            { "texto": "JAJAJAJAJAJJAJAJAJAJA", "author": "Copas" },
            { "texto": "Mi victoria estaba clara, tengo a Dios de mi lado.", "author": "Copas" },
            { "texto": "No me rendiré. Me volveré más fuerte y algún día caerás.", "author": "Copas" },
            { "texto": "A tu casa, niñate", "author": "Copas" }
        ],
        "scale": 0.5,
        "derrotado": false,
        "isBoss": true,
        "recompensa": 
        { 
            "name": "trozo",
            "description": "trozo de constitución",
            "effect": 0,
            "x": 800,
            "y": 700,
            "amountOfEffect": 10,
            "recogido": "false"
        }
        
    },
    "PITIBANCO ROJO":{
        "frases":[
            { "texto": "Hola, soy Piti Banco, el banco del piti.", "author": "PitiBanco Rojo" },
            { "texto": "¿Te quieres fumar uno?", "author": "PitiBanco Rojo" },
            { "texto": "¡Son muy saludables y te mejoran el ánimo!", "author": "PitiBanco Rojo" },
            { "texto": "Pero recuerda, solo uno de cada, eh?", "author": "PitiBanco Rojo" },
            { "texto": "Que nos conocemos, amigue.", "author": "PitiBanco Rojo" }
        ],
        "isPitiBanco": true,
        "fumado": "Ey ey ey pequeñe, ya te lo has fumado",
        "curarAnsiedad": "true",
        "curarVida": "true",
        "scale": 0.3
        
    },
    "PITIBANCO AMARILLO":{
        "frases":[
            { "texto": "Hola, soy Piti Banco, el banco del piti.", "author": "PitiBanco Rojo" },
            { "texto": "¿Te quieres fumar uno?", "author": "PitiBanco Rojo" },
            { "texto": "¡Son muy saludables y te mejoran el ánimo!", "author": "PitiBanco Rojo" },
            { "texto": "Pero recuerda, solo uno de cada, eh?", "author": "PitiBanco Rojo" },
            { "texto": "Que nos conocemos, amigue.", "author": "PitiBanco Rojo" }
        ],
        "isPitiBanco": true,
        "fumado": "Ey ey ey pequeñe, ya te lo has fumado",
        "curarAnsiedad": "true",
        "curarVida": "true",
        "scale": 0.3
        
    },
    "PITIBANCO AZUL":{
        "frases":[
            { "texto": "Hola, soy Piti Banco, el banco del piti.", "author": "PitiBanco Rojo" },
            { "texto": "¿Te quieres fumar uno?", "author": "PitiBanco Rojo" },
            { "texto": "¡Son muy saludables y te mejoran el ánimo!", "author": "PitiBanco Rojo" },
            { "texto": "Pero recuerda, solo uno de cada, eh?", "author": "PitiBanco Rojo" },
            { "texto": "Que nos conocemos, amigue.", "author": "PitiBanco Rojo" }
        ],
        "isPitiBanco": true,
        "fumado": "Ey ey ey pequeñe, ya te lo has fumado",
        "curarAnsiedad": "true",
        "curarVida": "true",
        "scale": 0.3
        
    },
    "PITIBANCO VERDE":{
        "frases":[
            { "texto": "Hola, soy Piti Banco, el banco del piti.", "author": "PitiBanco Rojo" },
            { "texto": "¿Te quieres fumar uno?", "author": "PitiBanco Rojo" },
            { "texto": "¡Son muy saludables y te mejoran el ánimo!", "author": "PitiBanco Rojo" },
            { "texto": "Pero recuerda, solo uno de cada, eh?", "author": "PitiBanco Rojo" },
            { "texto": "Que nos conocemos, amigue.", "author": "PitiBanco Rojo" }
        ],
        "isPitiBanco": true,
        "fumado": "Ey ey ey pequeñe, ya te lo has fumado",
        "curarAnsiedad": "true",
        "curarVida": "true",
        "scale": 0.3
        
    },
    "YUSOA":{
        "frases":[
            { "texto": "¡YUSOA! Tu reinado de terror termina hoy.", "author": "Elle" },
            { "texto": "¿Pero tú quién eres?", "author": "Yusoa" },
            { "texto": "Soy Elle y junto con la resistencia de Ellie Williams vengo a derrocarte.", "author": "Elle" },
            { "texto": "JAJAJAJA", "author": "Yusoa" },
            { "texto": "Ni me llegas a la suela de la garra, te podría aplastar facilmente.", "author": "Yusoa" },
            { "texto": "¡Yusoa no me vas a intimidar, he venido aquí con un solo objetivo y lo voy a cumplir!", "author": "Elle" }
        ],
        "victory":[
            { "texto": "¿Cómo ha podido este insignificante ser derrotarme?", "author": "Yusoa" },
            { "texto": "¡Ciudadanos de Madrizz, alzaos con el poder! ", "author": "Elle" },
            { "texto": "AAAAGGHHHH DESTROZARÉ TODO Y A TODOS", "author": "Yusoa" },
            { "texto": "Tchh, que mal perder que tienes, aceptalo, te hemos ganado justamente ", "author": "Elle" },
            { "texto": "VOLVERÉ Y VOLVERÉ MÁS FUERTE ", "author": "Yusoa" },
            { "video": "victoria" },
            { "texto": "Finalmente, hemos ganado.", "author": "Elle" }
           
            
        ],
        "lose":[
            { "texto": "Has perdido mocose JAJAJAJAJAJ ", "author": "Yusoa" },
            { "texto": "Lo siento, no he podido cumplir mi promesa.", "author": "Elle" },
            { "texto": "JAJAJA YO GANOOOO Y TU PIERDESSS.", "author": "Yusoa" },
            { "texto": "Cuando me vuelva más fuerte verás, nos volveremos a ver en breves.", "author": "Elle" }
            
        ],
        "scale": 1,
        "isBoss": true,
        "derrotado": false
        
    }
    
}

